yamlifier/__init__.py
yamlifier/generate.py
yamlifier-1.0.1.dist-info/DESCRIPTION.rst
yamlifier-1.0.1.dist-info/entry_points.txt
yamlifier-1.0.1.dist-info/METADATA
yamlifier-1.0.1.dist-info/metadata.json
yamlifier-1.0.1.dist-info/RECORD
yamlifier-1.0.1.dist-info/top_level.txt
yamlifier-1.0.1.dist-info/WHEEL
