Metadata-Version: 2.0
Name: yamlifier
Version: 1.0.1
Summary: Utility to create yaml files from a template. Perfect for cloud-config or cloud-init creation.
Home-page: https://github.com/greenqloud/yamlifier
Author: Greenqloud
Author-email: UNKNOWN
License: Apache
Keywords: yaml,cloud-init,cloud-config
Platform: UNKNOWN
Classifier: Development Status :: 5 - Production/Stable
Classifier: License :: OSI Approved :: Apache Software License
Classifier: Intended Audience :: Information Technology
Classifier: Operating System :: OS Independent
Classifier: Programming Language :: Python
Classifier: Programming Language :: Python :: 2
Classifier: Programming Language :: Python :: 2.7
Classifier: Programming Language :: Python :: 3
Classifier: Programming Language :: Python :: 3.5
Classifier: Topic :: Software Development :: Libraries :: Python Modules
Requires-Dist: ruamel.yaml (==0.14.2)
